README
setup.py
src/django_meio_shorturl.egg-info/PKG-INFO
src/django_meio_shorturl.egg-info/SOURCES.txt
src/django_meio_shorturl.egg-info/dependency_links.txt
src/django_meio_shorturl.egg-info/requires.txt
src/django_meio_shorturl.egg-info/top_level.txt
src/shorturl/__init__.py
src/shorturl/baseconv.py
src/shorturl/conf.py
src/shorturl/core.py
src/shorturl/exceptions.py
src/shorturl/models.py
src/shorturl/testsettings.py
src/shorturl/urls.py
src/shorturl/views.py
src/shorturl/tests/__init__.py
src/shorturl/tests/models.py
src/shorturl/tests/test_baseconv.py
src/shorturl/tests/test_core.py
src/shorturl/tests/test_views.py