Metadata-Version: 1.0
Name: django-meio-shorturl
Version: 1.0
Summary: Short URL handling in Django apps.
Home-page: http://github.com/vbmendes/django-meio-shorturl
Author: Vinicius Mendes
Author-email: vbmendes@gmail.com
License: BSD
Platform: UNKNOWN
Classifier: Development Status :: 3 - Alpha
Classifier: Framework :: Django
Classifier: Intended Audience :: Developers
Classifier: License :: OSI Approved :: BSD License
Classifier: Natural Language :: English
Classifier: Operating System :: OS Independent
Classifier: Programming Language :: Python
Classifier: Topic :: Internet :: WWW/HTTP
Classifier: Topic :: Software Development :: Libraries :: Python Modules
